indisynth/__init__.py
indisynth/agriculture.py
indisynth/banking_finance.py
indisynth/business_operations.py
indisynth/business_tax.py
indisynth/contact_address.py
indisynth/education.py
indisynth/employment.py
indisynth/government_benefits.py
indisynth/healthcare.py
indisynth/legal_documentation.py
indisynth/personal_identity.py
indisynth/professional.py
indisynth/property_number.py
indisynth/travel_tourism.py
indisynth/utilities.py
indisynth/vehicle.py
IndiSynth-1.0.3.dist-info/METADATA
IndiSynth-1.0.3.dist-info/WHEEL
IndiSynth-1.0.3.dist-info/top_level.txt
IndiSynth-1.0.3.dist-info/RECORD
