Metadata-Version: 2.2
Name: IndiSynth
Version: 1.0.3
Summary: A comprehensive synthetic data generator for Indian entities.
Home-page: https://github.com/srinrealyf/indisynth
Author: Sai Raam
Author-email: srinrealyf@gmail.com
License: Apache License 2.0
Classifier: Programming Language :: Python :: 3
Classifier: License :: OSI Approved :: Apache Software License
Classifier: Operating System :: OS Independent
Requires-Python: >=3.6
Dynamic: author
Dynamic: author-email
Dynamic: classifier
Dynamic: description
Dynamic: description-content-type
Dynamic: home-page
Dynamic: license
Dynamic: requires-python
Dynamic: summary
